django_simple_api/__init__.py
django_simple_api/__version__.py
django_simple_api/_fields.py
django_simple_api/apps.py
django_simple_api/decorators.py
django_simple_api/exceptions.py
django_simple_api/extras.py
django_simple_api/fields.py
django_simple_api/middleware.py
django_simple_api/params.py
django_simple_api/schema.py
django_simple_api/serialize.py
django_simple_api/types.py
django_simple_api/urls.py
django_simple_api/utils.py
django_simple_api/views.py
django_simple_api/static/redoc.standalone.js
django_simple_api/static/swagger-ui-bundle.js
django_simple_api/static/swagger-ui.css
django_simple_api/templates/redoc.html
django_simple_api/templates/swagger.html
django_simple_api-0.2.2.dist-info/LICENSE
django_simple_api-0.2.2.dist-info/METADATA
django_simple_api-0.2.2.dist-info/WHEEL
django_simple_api-0.2.2.dist-info/top_level.txt
django_simple_api-0.2.2.dist-info/RECORD
