Metadata-Version: 2.1
Name: django-simple-api
Version: 0.2.2
Summary: A non-intrusive component that can help you quickly create APIs.
Home-page: https://github.com/Django-Simple-API/django-simple-api
Author: abersheeran
Author-email: me@abersheeran.com
Maintainer: waitan2018
Requires-Python: >=3.7,<4.0
License-File: LICENSE
Requires-Dist: Pillow (<9.0.0,>=8.2.0)
Requires-Dist: django
Requires-Dist: pydantic (<2.0.0,>=1.8.1)
